LICENSE
MANIFEST.in
README.rst
setup.py
txkoji/__init__.py
txkoji/build.py
txkoji/build_states.py
txkoji/cache.py
txkoji/call.py
txkoji/channel.py
txkoji/connection.py
txkoji/estimates.py
txkoji/exceptions.py
txkoji/marshaller.py
txkoji/messages.py
txkoji/package.py
txkoji/query_factory.py
txkoji/ssl.py
txkoji/task.py
txkoji/task_states.py
txkoji.egg-info/PKG-INFO
txkoji.egg-info/SOURCES.txt
txkoji.egg-info/dependency_links.txt
txkoji.egg-info/not-zip-safe
txkoji.egg-info/requires.txt
txkoji.egg-info/top_level.txt