Metadata-Version: 1.1
Name: txkoji
Version: 0.10.0
Summary: Twisted API for Koji
Home-page: https://github.com/ktdreyer/txkoji
Author: Ken Dreyer
Author-email: ktdreyer@ktdreyer.com
License: MIT
Keywords: koji,twisted
Platform: UNKNOWN
Classifier: Development Status :: 4 - Beta
Classifier: Framework :: Twisted
Classifier: Intended Audience :: Developers
Classifier: License :: OSI Approved :: MIT License
Classifier: Operating System :: OS Independent
Classifier: Programming Language :: Python :: 2.7
Classifier: Programming Language :: Python :: 3.6
